LICENCE
MANIFEST.in
README.rst
setup.cfg
setup.py
bambumapa.egg-info/PKG-INFO
bambumapa.egg-info/SOURCES.txt
bambumapa.egg-info/dependency_links.txt
bambumapa.egg-info/requires.txt
bambumapa.egg-info/top_level.txt
mapa/__init__.py
mapa/admin copy.py
mapa/admin.py
mapa/apps.py
mapa/forms.py
mapa/models.py
mapa/tests.py
mapa/urls.py
mapa/views.py
mapa/migrations/0001_initial.py
mapa/migrations/__init__.py
mapa/templates/.DS_Store
mapa/templates/mapa/.DS_Store
mapa/templates/mapa/areabambu/detallu.html
mapa/templates/mapa/areabambu/django.code-workspace
mapa/templates/mapa/areabambu/input.html
mapa/templates/mapa/areabambu/lista.html
mapa/templates/mapa/areabambu/update copy.html
mapa/templates/mapa/areabambu/update.html
mapa/templates/mapa/grupubambu/detallu.html
mapa/templates/mapa/grupubambu/django.code-workspace
mapa/templates/mapa/grupubambu/input.html
mapa/templates/mapa/grupubambu/inputimportasaunbambu.html
mapa/templates/mapa/grupubambu/lista.html
mapa/templates/mapa/grupubambu/rejistuimportasaunbambu.html
mapa/templates/mapa/grupubambu/update copy.html
mapa/templates/mapa/grupubambu/update.html
mapa/templates/mapa/grupuviveirus/detallu.html
mapa/templates/mapa/grupuviveirus/django.code-workspace
mapa/templates/mapa/grupuviveirus/input.html
mapa/templates/mapa/grupuviveirus/lista.html
mapa/templates/mapa/grupuviveirus/update copy.html
mapa/templates/mapa/grupuviveirus/update.html
mapa/views/__init__.py
mapa/views/view_areabambu.py
mapa/views/view_grupubambu.py
mapa/views/view_grupuviveirus.py